{
   "weather_details": {
      "21/02/2024": {
         "rainfall": 0,
         "t_max": 33,
         "t_min": 21,
         "rh_max": 76,
         "rh_min": 37,
         "wind_speed": 27,
         "wind_direction": 207,
         "cloud_cover": 0
      },
      "22/02/2024": {
         "rainfall": 0,
         "t_max": 34,
         "t_min": 21,
         "rh_max": 76,
         "rh_min": 35,
         "wind_speed": 26,
         "wind_direction": 202,
         "cloud_cover": 2
      },
      "23/02/2024": {
         "rainfall": 2,
         "t_max": 32,
         "t_min": 21,
         "rh_max": 82,
         "rh_min": 45,
         "wind_speed": 16,
         "wind_direction": 204,
         "cloud_cover": 5
      },
      "24/02/2024": {
         "rainfall": 15,
         "t_max": 31,
         "t_min": 22,
         "rh_max": 82,
         "rh_min": 43,
         "wind_speed": 12,
         "wind_direction": 202,
         "cloud_cover": 7
      },
      "25/02/2024": {
         "rainfall": 5,
         "t_max": 31,
         "t_min": 20,
         "rh_max": 88,
         "rh_min": 53,
         "wind_speed": 7,
         "wind_direction": 90,
         "cloud_cover": 7
      }
   },
   "names_of_crops": [
      "paddy",
      "mustard",
      "groundnut",
      "cashew",
      "potato",
      "blackgram",
      "greengram",
      "tobacco",
      "brinjal",
      "cole crops"
   ],
   "general_advisory": "It is recommended to apply pre-emergence herbicides in paddy fields, manage Bacterial Leaf Blight in paddy, control stem and root borer in cashew, sow Cowpea, Cluster bean, Pumpkin, Cucumber, and Watermelon in February-March, transplant vegetables in the afternoon to avoid high temperature, harvest mustard and potato crops at the right time, manage Tobacco Caterpillar pest, and follow specific management practices for different crops mentioned in the advisory.",
   "crops_data": {
      "paddy": {
         "advisory": [
            "Apply 35 kg Urea per acre at 3 weeks after transplanting for high yielding paddy varieties"
         ]
      },
      "mustard": {
         "advisory": [
            "Harvest the mustard crop as soon as the pods turn yellowish-brown to avoid shattering"
         ]
      },
      "groundnut": {
         "advisory": [
            "To manage Tobacco Caterpillar pest in Groundnut, Blackgram, Greengram proper surveillance should be done to collect and destroy egg mass and caterpillar of the pest"
         ]
      },
      "cashew": {
         "advisory": [
            "To manage stem borer in cashew remove minimum width of the bark retaining at least 50% of the bark circumference"
         ]
      },
      "potato": {
         "advisory": [
            "Harvest the potato crop which are at 75-85 days after planting and when majority of the leaves turn yellowish brown"
         ]
      },
      "blackgram": {
         "advisory": [
            "To control aphids during primary stage of pest infestation spray Neem Based Pesticide (Azadirachtin) @ 600 ml/acre"
         ]
      },
      "greengram": {
         "advisory": [
            "To control aphids during primary stage of pest infestation spray Neem Based Pesticide (Azadirachtin) @ 600 ml/acre"
         ]
      },
      "tobacco": {
         "advisory": [
            "To manage Tobacco Caterpillar pest proper surveillance should be done and Pheromone traps should be set up"
         ]
      },
      "brinjal": {
         "advisory": [
            "To manage little leaf in brinjal remove infected plants and spray recommended pesticides"
         ]
      },
      "cole crops": {
         "advisory": [
            "To manage leaf webber and head borer pests, regular monitoring of pest infestation should be carried out and specific pesticides should be applied"
         ]
      }
   },
   "date": "20-02-2024"
}