{
   "Institution": {
      "Orissa University of Agriculture & Technology": "Bhubaneswar"
   },
   "Bulletin_Details": {
      "Week_Number": "09",
      "District": "NAYAGARH(Odisha)",
      "Bulletin_Number": "2024",
      "Date": "09-02-2024"
   },
   "Weather_Condition_Last_Week": {
      "Period": "2024-02-09 - 2024-02-14",
      "Rainfall_mm": 4.0,
      "Max_Temperature_C": "31.0",
      "Min_Temperature_C": "17.0"
   },
   "Forecast_Up_To": {
      "Date": "2024-02-14",
      "Description": "As per IMD forecast, no to very light rainfall is expected for next 5 days and the weather will be sunny and dry. Maximum temperature will vary from 30째C- 31째C and minimum temperature will vary from 17째C to 19째C. The range of maximum humidity may remain 57%-90% and minimum humidity may remain 18%-28%. Cloud cover will be 0-7 octa. Wind speed may vary from 6-8 kmph."
   },
   "Daily_Weather_Data": [],
   "Agromet_Advisory": {
      "General_Advisory": "Dry weather is likely to prevail in the district.",
      "SMS_Advisory": "Dry weather is likely to prevail in the district.",
      "Crop_Specific_Advisory": [
         {
            "Crop": "PIGEON PEA  (RED GRAM/ARHAR)",
            "Advisory": "Inorder to control leaf blight in pigeon pea, spray Chlorothalonil @ 400 g in 200 litres of water per acre of land."
         },
         {
            "Crop": "PIGEON PEA  (RED GRAM/ARHAR)",
            "Advisory": "Pod borer in pigeon pea cultivation has been noticed in some places. Spray Chlorantraniliprole @ 80 ml in 200 litres of water per acre of land to control it."
         },
         {
            "Crop": "GREEN GRAM",
            "Advisory": "Treat the green gram seeds with Vitavax power (Carboxyn + Thiram) @ 2 gm or Gaucho (Imidachloprid 600 FS) @ 5 ml per kg of seeds before sowing in the main field."
         }
      ]
   },
   "Contact_Information": {},
   "Additional_Resources": {
      "OUAT_KALINGA_Products": "Unutilised small pieces of paddy straw can be used in oyster mushroom production so that cost of cultivation as well as manual work can be reduced.",
      "Meghdoot_Mobile_App": {}
   },
   "date": "09-02-2024"
}