{
   "weather_details": {
      "29-06-2024": {
         "rainfall": 20,
         "t_max": 29,
         "t_min": 21,
         "rh_max": 85,
         "rh_min": 62,
         "wind_speed": 19,
         "wind_direction": 248,
         "cloud_cover": 8
      },
      "30-06-2024": {
         "rainfall": 12,
         "t_max": 29,
         "t_min": 22,
         "rh_max": 86,
         "rh_min": 63,
         "wind_speed": 17,
         "wind_direction": 249,
         "cloud_cover": 8
      },
      "01-07-2024": {
         "rainfall": 4,
         "t_max": 33,
         "t_min": 23,
         "rh_max": 85,
         "rh_min": 61,
         "wind_speed": 18,
         "wind_direction": 243,
         "cloud_cover": 6
      },
      "02-07-2024": {
         "rainfall": 2,
         "t_max": 33,
         "t_min": 24,
         "rh_max": 84,
         "rh_min": 56,
         "wind_speed": 17,
         "wind_direction": 248,
         "cloud_cover": 5
      },
      "03-07-2024": {
         "rainfall": 2,
         "t_max": 34,
         "t_min": 25,
         "rh_max": 79,
         "rh_min": 55,
         "wind_speed": 20,
         "wind_direction": 246,
         "cloud_cover": 4
      }
   },
   "names_of_crops": [
      "rice",
      "maize",
      "ragi",
      "tomato",
      "brinjal",
      "ginger",
      "turmeric"
   ],
   "general_advisory": "Rainfall is expected during the next five days, farmers are advised to take proper precautions. Proper storage of rainwater is recommended for irrigation. Field preparation for non-paddy crops is advised. Pesticide measures are recommended due to high humidity.",
   "crops_data": {
      "rice": {
         "advisory": [
            "Complete sowing where direct seeding is practiced with proper fertilization",
            "Raise nursery for transplanted kharif rice with appropriate nutrients"
         ]
      },
      "maize": {
         "advisory": [
            "Optimum time for sowing maize with proper land preparation and fertilization"
         ]
      },
      "ragi": {
         "advisory": [
            "Optimum time for direct sowing ragi with specific seeding instructions"
         ]
      },
      "tomato": {
         "advisory": [
            "Apply specific pesticides for bacterial wilting in tomato"
         ]
      },
      "brinjal": {
         "advisory": [
            "Control fruit and shoot borer with neem-based pesticide in brinjal",
            "Apply specific pesticides for fruit rot infestation in chilli and brinjal"
         ]
      },
      "ginger": {
         "advisory": [
            "Grow ginger with recommended seed rate and fertilization practices"
         ]
      },
      "turmeric": {
         "advisory": [
            "Grow turmeric with recommended seed rate and land preparation practices"
         ]
      }
   },
   "date": "28-06-2024"
}